eventx.py
eventx-0.1.1.dist-info/licenses/LICENSE
eventx-0.1.1.dist-info/METADATA
eventx-0.1.1.dist-info/WHEEL
eventx-0.1.1.dist-info/top_level.txt
eventx-0.1.1.dist-info/zip-safe
eventx-0.1.1.dist-info/RECORD
