Metadata-Version: 2.4
Name: eventx
Version: 0.1.1
Summary: Event-driven messaging via exceptions - Ultra-lightweight event system
Home-page: https://github.com/Tryboy869/eventx
Author: Anzize Daouda
Author-email: Anzize Daouda <nexusstudio100@gmail.com>
Maintainer-email: Anzize Daouda <nexusstudio100@gmail.com>
License: MIT
Project-URL: Homepage, https://github.com/Tryboy869/eventx
Project-URL: Repository, https://github.com/Tryboy869/eventx
Project-URL: Documentation, https://github.com/Tryboy869/eventx#readme
Project-URL: Bug Reports, https://github.com/Tryboy869/eventx/issues
Project-URL: Changelog, https://github.com/Tryboy869/eventx/releases
Keywords: events,messaging,exceptions,event-driven,lightweight,async-alternative,microservices,python,raise,exception-based
Classifier: Development Status :: 4 - Beta
Classifier: Intended Audience :: Developers
Classifier: Topic :: Software Development :: Libraries :: Python Modules
Classifier: Topic :: System :: Distributed Computing
Classifier: Topic :: Software Development :: Object Brokering
Classifier: License :: OSI Approved :: MIT License
Classifier: Programming Language :: Python :: 3
Classifier: Programming Language :: Python :: 3.8
Classifier: Programming Language :: Python :: 3.9
Classifier: Programming Language :: Python :: 3.10
Classifier: Programming Language :: Python :: 3.11
Classifier: Programming Language :: Python :: 3.12
Classifier: Programming Language :: Python :: 3.13
Classifier: Operating System :: OS Independent
Classifier: Typing :: Typed
Requires-Python: >=3.8
License-File: LICENSE
Provides-Extra: dev
Requires-Dist: pytest>=7.4.0; extra == "dev"
Requires-Dist: pytest-cov>=4.1.0; extra == "dev"
Requires-Dist: black>=23.0.0; extra == "dev"
Requires-Dist: flake8>=6.0.0; extra == "dev"
Requires-Dist: mypy>=1.5.0; extra == "dev"
Requires-Dist: isort>=5.12.0; extra == "dev"
Provides-Extra: test
Requires-Dist: pytest>=7.4.0; extra == "test"
Requires-Dist: pytest-cov>=4.1.0; extra == "test"
Dynamic: author
Dynamic: home-page
Dynamic: license-file
Dynamic: requires-python
